english_word_note_mcp/__init__.py
english_word_note_mcp/db_model.py
english_word_note_mcp/models.py
english_word_note_mcp/server.py
english_word_note_mcp/data/english_words.base.json
english_word_note_mcp-0.1.3.dist-info/METADATA
english_word_note_mcp-0.1.3.dist-info/WHEEL
english_word_note_mcp-0.1.3.dist-info/entry_points.txt
english_word_note_mcp-0.1.3.dist-info/RECORD
