Metadata-Version: 2.4
Name: english-word-note-mcp
Version: 0.1.3
Summary: Add your description here
Author-email: tiebingice <1206345694@qq.com>
Requires-Python: >=3.11
Requires-Dist: aiofiles<24.0,>=22.0
Requires-Dist: aiomysql>=0.2.0
Requires-Dist: aiosqlite>=0.21.0
Requires-Dist: mcp[cli]==1.8.0
Requires-Dist: orjson>=3.10.18
Requires-Dist: sqlmodel>=0.0.24
